monailabel/__init__.py
monailabel/_version.py
monailabel/app.py
monailabel/config.py
monailabel/logging.json
monailabel/main.py
monailabel/client/__init__.py
monailabel/client/client.py
monailabel/datastore/__init__.py
monailabel/datastore/cvat.py
monailabel/datastore/dicom.py
monailabel/datastore/dsa.py
monailabel/datastore/local.py
monailabel/datastore/xnat.py
monailabel/datastore/utils/__init__.py
monailabel/datastore/utils/colors.py
monailabel/datastore/utils/convert.py
monailabel/datastore/utils/dicom.py
monailabel/deepedit/__init__.py
monailabel/deepedit/handlers.py
monailabel/deepedit/interaction.py
monailabel/deepedit/transforms.py
monailabel/endpoints/__init__.py
monailabel/endpoints/activelearning.py
monailabel/endpoints/batch_infer.py
monailabel/endpoints/datastore.py
monailabel/endpoints/infer.py
monailabel/endpoints/info.py
monailabel/endpoints/login.py
monailabel/endpoints/logs.py
monailabel/endpoints/model.py
monailabel/endpoints/ohif.py
monailabel/endpoints/proxy.py
monailabel/endpoints/scoring.py
monailabel/endpoints/session.py
monailabel/endpoints/train.py
monailabel/endpoints/wsi_infer.py
monailabel/endpoints/static/.gitignore
monailabel/endpoints/static/favicon.ico
monailabel/endpoints/static/ohif/031089e563a18ada8441.wasm
monailabel/endpoints/static/ohif/1185.bundle.63d4a7234e943a3bc2ab.js
monailabel/endpoints/static/ohif/1266.bundle.336f6cdc0a45bd0e2c68.js
monailabel/endpoints/static/ohif/1266.css
monailabel/endpoints/static/ohif/1374.bundle.8807bfaa6e4d720661ce.js
monailabel/endpoints/static/ohif/149.bundle.b8d177954628f4631fc0.js
monailabel/endpoints/static/ohif/1520.bundle.acba7d34f1203a4b294c.js
monailabel/endpoints/static/ohif/17dd54813d5acc10bf8f.wasm
monailabel/endpoints/static/ohif/1801.css
monailabel/endpoints/static/ohif/1927.bundle.40b115cd925087e88f6f.js
monailabel/endpoints/static/ohif/2068.bundle.83ad900b6ad2110750da.js
monailabel/endpoints/static/ohif/20fc4c659b85ccd2a9c0.wasm
monailabel-0.8.5.dist-info/LICENSE
monailabel-0.8.5.dist-info/METADATA
monailabel-0.8.5.dist-info/WHEEL
monailabel-0.8.5.dist-info/top_level.txt
monailabel-0.8.5.dist-info/RECORD
