Metadata-Version: 2.1
Name: monailabel
Version: 0.8.5
Summary: Active Learning Toolkit for Healthcare Imaging
Home-page: https://monai.io/
Author: MONAI Consortium
Author-email: monai.contact@gmail.com
License: Apache License 2.0
Project-URL: Documentation, https://docs.monai.io/
Project-URL: Bug Tracker, https://github.com/Project-MONAI/MONAILabel/issues
Project-URL: Source Code, https://github.com/Project-MONAI/MONAILabel
Platform: OS Independent
Requires-Python: >=3.9
License-File: LICENSE
Requires-Dist: monai[fire,gdown,ignite,itk,lmdb,mlflow,nibabel,openslide,pillow,psutil,skimage,tensorboard,torchvision,tqdm]>=1.4.0
Requires-Dist: uvicorn>=0.29.0
Requires-Dist: pydantic>=2.7.0
Requires-Dist: pydantic-settings>=2.2.1
Requires-Dist: python-dotenv>=1.0.1
Requires-Dist: fastapi>=0.110.2
Requires-Dist: python-multipart>=0.0.9
Requires-Dist: httpx>=0.27.0
Requires-Dist: schedule>=1.2.1
Requires-Dist: dicomweb-client[gcp]>=0.59.1
Requires-Dist: timeloop>=1.0.2
Requires-Dist: expiringdict>=1.2.2
Requires-Dist: expiring_dict>=1.1.0
Requires-Dist: cachetools>=5.3.3
Requires-Dist: watchdog>=4.0.0
Requires-Dist: pydicom>=2.4.4
Requires-Dist: pydicom-seg>=0.4.1
Requires-Dist: pynetdicom>=2.0.2
Requires-Dist: pynrrd>=1.0.0
Requires-Dist: numpymaxflow>=0.0.7
Requires-Dist: girder-client>=3.2.3
Requires-Dist: ninja>=1.11.1.1
Requires-Dist: einops>=0.7.0
Requires-Dist: pyyaml>=6.0.1
Requires-Dist: filelock>=3.11.0
Requires-Dist: passlib>=1.7.4
Requires-Dist: pyjwt>=2.8.0
Requires-Dist: bcrypt>=4.1.2
Requires-Dist: shapely>=2.0.4
Requires-Dist: requests>=2.31.0
Requires-Dist: requests-toolbelt>=1.0.0
Requires-Dist: urllib3>=2.2.1
Requires-Dist: scikit-learn
Requires-Dist: scipy
Requires-Dist: google-auth>=2.29.0
Requires-Dist: sam2>=0.4.1; python_version >= "3.10"
